{
  "slices": {
    "__TYPE__": "SliceContentType",
    "value": [
      {
        "key": "landing$4c1c3ee5-4aee-4cea-83d0-9b4a607cf24a",
        "name": "landing",
        "widget": {
          "__TYPE__": "SharedSliceContent",
          "variation": "default",
          "primary": {
            "title": {
              "__TYPE__": "StructuredTextContent",
              "value": [
                {
                  "type": "heading1",
                  "content": {
                    "text": "Topic"
                  }
                }
              ]
            },
            "description": {
              "__TYPE__": "StructuredTextContent",
              "value": [
                {
                  "type": "paragraph",
                  "content": {
                    "text": "Adipisicing occaecat amet dolore."
                  }
                }
              ]
            }
          },
          "items": [
            {
              "__TYPE__": "GroupItemContent",
              "value": []
            }
          ]
        }
      },
      {
        "key": "notification$5987b781-2ac2-489b-9e74-52a05395abd2",
        "name": "notification",
        "widget": {
          "__TYPE__": "SharedSliceContent",
          "variation": "default",
          "primary": {
            "title": {
              "__TYPE__": "StructuredTextContent",
              "value": [
                {
                  "type": "heading1",
                  "content": {
                    "text": "Breath"
                  }
                }
              ]
            },
            "description": {
              "__TYPE__": "StructuredTextContent",
              "value": [
                {
                  "type": "paragraph",
                  "content": {
                    "text": "Cillum ex qui proident aliquip mollit tempor officia aliquip nostrud laborum enim eiusmod dolor."
                  }
                }
              ]
            },
            "button": {
              "__TYPE__": "LinkContent",
              "value": {
                "__TYPE__": "ExternalLink",
                "url": "http://twitter.com"
              }
            },
            "return": {
              "__TYPE__": "LinkContent",
              "value": {
                "__TYPE__": "ExternalLink",
                "url": "https://prismic.io"
              }
            }
          },
          "items": [
            {
              "__TYPE__": "GroupItemContent",
              "value": []
            }
          ]
        }
      },
      {
        "key": "ratings$ac799da6-9478-4242-90ec-58c5e3adf9b6",
        "name": "ratings",
        "widget": {
          "__TYPE__": "SharedSliceContent",
          "variation": "default",
          "primary": {
            "satisfied_percent": {
              "__TYPE__": "FieldContent",
              "value": "nodded",
              "type": "Text"
            },
            "satisfied_text": {
              "__TYPE__": "FieldContent",
              "value": "done",
              "type": "Text"
            },
            "neutral_percent": {
              "__TYPE__": "FieldContent",
              "value": "chair",
              "type": "Text"
            },
            "neutral_text": {
              "__TYPE__": "FieldContent",
              "value": "choice",
              "type": "Text"
            },
            "unsatisfied_percent": {
              "__TYPE__": "FieldContent",
              "value": "kept",
              "type": "Text"
            },
            "unsatisfied_text": {
              "__TYPE__": "FieldContent",
              "value": "average",
              "type": "Text"
            }
          },
          "items": [
            {
              "__TYPE__": "GroupItemContent",
              "value": []
            }
          ]
        }
      },
      {
        "key": "log_in$9522155a-7102-41d6-9a42-5d6e48d1c174",
        "name": "log_in",
        "widget": {
          "__TYPE__": "SharedSliceContent",
          "variation": "default",
          "primary": {
            "title": {
              "__TYPE__": "StructuredTextContent",
              "value": [
                {
                  "type": "heading1",
                  "content": {
                    "text": "Thank"
                  }
                }
              ]
            },
            "description": {
              "__TYPE__": "StructuredTextContent",
              "value": [
                {
                  "type": "paragraph",
                  "content": {
                    "text": "Culpa ad mollit dolor deserunt ullamco nostrud reprehenderit elit. Pariatur enim commodo irure laborum."
                  }
                }
              ]
            },
            "button_text": {
              "__TYPE__": "FieldContent",
              "value": "transportation",
              "type": "Text"
            }
          },
          "items": [
            {
              "__TYPE__": "GroupItemContent",
              "value": []
            }
          ]
        }
      },
      {
        "key": "testimonial$94edf0b8-d98a-41c8-97ce-b09ebea1de48",
        "name": "testimonial",
        "widget": {
          "__TYPE__": "SharedSliceContent",
          "variation": "default",
          "primary": {
            "title": {
              "__TYPE__": "StructuredTextContent",
              "value": [
                {
                  "type": "heading1",
                  "content": {
                    "text": "Headed"
                  }
                }
              ]
            },
            "description": {
              "__TYPE__": "StructuredTextContent",
              "value": [
                {
                  "type": "paragraph",
                  "content": {
                    "text": "Proident esse velit dolore ullamco. Anim aliqua veniam reprehenderit cupidatat in proident fugiat elit exercitation."
                  }
                }
              ]
            },
            "author_name": {
              "__TYPE__": "FieldContent",
              "value": "written",
              "type": "Text"
            }
          },
          "items": [
            {
              "__TYPE__": "GroupItemContent",
              "value": []
            }
          ]
        }
      },
      {
        "key": "food_card$3b3ce634-77a9-4db2-8c7b-9ec26ccce0aa",
        "name": "food_card",
        "widget": {
          "__TYPE__": "SharedSliceContent",
          "variation": "default",
          "primary": {
            "title": {
              "__TYPE__": "StructuredTextContent",
              "value": [
                {
                  "type": "heading1",
                  "content": {
                    "text": "Central"
                  }
                }
              ]
            },
            "description": {
              "__TYPE__": "StructuredTextContent",
              "value": [
                {
                  "type": "paragraph",
                  "content": {
                    "text": "In nulla incididunt incididunt nostrud quis non elit Lorem velit nostrud magna sunt."
                  }
                }
              ]
            },
            "rate": {
              "__TYPE__": "FieldContent",
              "value": "57",
              "type": "Number"
            }
          },
          "items": [
            {
              "__TYPE__": "GroupItemContent",
              "value": []
            }
          ]
        }
      }
    ]
  }
}